[
    {
        "id": 1,
        "name": "钢铁是怎么炼成的",
        "writer": "尼・奥斯特洛夫斯基",
        "introduction": "小说通过记叙保尔・柯察金的成长道路告诉人们，一个人只有在革命的艰难困苦中战胜敌人也战胜自己，只有在把自己的追求和祖国、人民的利益联系在一起的时候，才会创造出奇迹，才会成长为钢铁战士。",
        "versionDate": "1990-01-01"
    },
    {
        "id": 3,
        "name": "微机原理与接口技术――基于8086和Proteus仿真（第3版）",
        "writer": "顾晖,陈越,梁惺彦",
        "introduction": "本书从微机系统应用的角度出发，以Intel 8086微处理器和IBM PC系列微机为主要对象，系统介绍微机系统的基本组成、工作原理、接口技术及应用。本书在总结第2版内容的基础上，调整了章节设置，优化了各章节的内容及实例；增加了对Proteus下汇编语言编程方法的介绍；对第13章的综合实例也进行了调整，并对设计方案进行了详细说明。全书共13章，包括：数的表示与运算、8086微机系统、8086寻址方式与指令系统、8086汇编语言程序设计、Proteus仿真平台的使用、存储器、输入/输出接口、可编程接口芯片、中断与中断管理、数模与模数转换及应用、总线、Proteus仿真基础实例和Proteus仿真综合实例。 本书内容全面、实用性强，原理、技术与应用并重，并特别介绍了利用EDA工具――Proteus 8的实验方法，讲述有特点和新意。本书在实例讲解方面进一步加强，书中提供的实例全部在Proteus 8中调试通过，并配套实例演示视频。实例设计方案同时适用于实验箱实验的教学方式。 本书可作为高等院校电气类与电子信息类各专业本科生的教材，也可作为研究生教材或供有关工程技术人员参考使用。",
        "versionDate": "2019-09-01"
    }
]